dorky/__about__.py
dorky/__init__.py
dorky/helper.py
dorky/security.py
dorky/service.py
dorky/types.py
dorky/impl/jsonfile.py
dorky/impl/sqlite.py
dorky-0.0.1.dist-info/METADATA
dorky-0.0.1.dist-info/WHEEL
dorky-0.0.1.dist-info/licenses/LICENSE.txt
dorky-0.0.1.dist-info/RECORD
